rc4me/__init__.py
rc4me/cli.py
rc4me/cli_test.py
rc4me/conftest.py
rc4me/prepare_repo.py
rc4me/rcmanager.py
rc4me/rcmanager_test.py
rc4me-0.1.1.dist-info/METADATA
rc4me-0.1.1.dist-info/WHEEL
rc4me-0.1.1.dist-info/entry_points.txt
rc4me-0.1.1.dist-info/top_level.txt
rc4me-0.1.1.dist-info/RECORD
