Metadata-Version: 2.1
Name: rc4me
Version: 0.1.1
Summary: Description
Home-page: https://github.com/wiggums-analytics/rc4me
Author: Michael Stefferson/Jeffrey Moore
Author-email: mstefferson@gmail.com
License: MIT License
Project-URL: Bug Tracker, https://github.com/wiggums-analytics/rc4me/issues
Platform: UNKNOWN
Requires-Python: >=3.8
Requires-Dist: click (>=7.1.2)
Requires-Dist: pick (>=1.0.0)
Requires-Dist: gitpython (>=3.1.11)
